process_mining_core/__init__.py
process_mining_core/algorithms/__init__.py
process_mining_core/algorithms/directly_follows_graph_creator.py
process_mining_core/algorithms/petri_net_creator.py
process_mining_core/algorithms/lossy_counting/__init__.py
process_mining_core/algorithms/lossy_counting/case_id_dictionary.py
process_mining_core/algorithms/lossy_counting/frequency_delta_pair.py
process_mining_core/algorithms/lossy_counting/lossy_counting_dictionary.py
process_mining_core/algorithms/stream_heuristics/__init__.py
process_mining_core/algorithms/stream_heuristics/heuristics_net_creator.py
process_mining_core/algorithms/tests/__init__.py
process_mining_core/algorithms/tests/heuristics_net_creator_test.py
process_mining_core/algorithms/tests/petri_net_creator_test.py
process_mining_core/algorithms/tests/petrinet_merger_test.py
process_mining_core/algorithms/tests/test_pipeline.py
process_mining_core/datastructure/__init__.py
process_mining_core/datastructure/converter/__init__.py
process_mining_core/datastructure/converter/heuristics_net_petri_net_converter.py
process_mining_core/datastructure/converter/petrinet_merger.py
process_mining_core/datastructure/core/__init__.py
process_mining_core/datastructure/core/case_id.py
process_mining_core/datastructure/core/directly_follows_relation.py
process_mining_core/datastructure/core/event.py
process_mining_core/datastructure/core/event_log.py
process_mining_core/datastructure/core/model/__init__.py
process_mining_core/datastructure/core/model/directly_follows_graph.py
process_mining_core/datastructure/core/model/heuristics_net.py
process_mining_core/datastructure/core/model/petri_net.py
process_mining_core/datastructure/wrapper/__init__.py
process_mining_core/datastructure/wrapper/recorded_event.py
process_mining_core/datastructure/wrapper/recorded_heuristics_net.py
process_mining_core-0.1.2.dist-info/METADATA
process_mining_core-0.1.2.dist-info/WHEEL
process_mining_core-0.1.2.dist-info/RECORD
