Metadata-Version: 2.3
Name: process-mining-core
Version: 0.1.2
Summary: A library for selected of process mining datastructures and algorithms
Project-URL: Homepage, https://github.com/HenryWedge/ProcessMiningCore
Author-email: Hendrik Reiter <hendrik.reiter@email.uni-kiel.de>
Classifier: Operating System :: OS Independent
Classifier: Programming Language :: Python :: 3
Requires-Python: >=3.8
